{
    "azureWebPubSub.reportIssue": "Report Issue...",
    "azureWebPubSub.description": "An Azure Web PubSub extension for Visual Studio Code.",
    "azureWebPubSub.enableOutputTimestamps": "Prepends each line displayed in the output channel with a timestamp.",
    "azureWebPubSub.common.refresh": "Refresh",
    "azureWebPubSub.common.toggleVisibility": "Toggle Visibility.",
    "azureWebPubSub.webPubSub.restart": "Restart Service",
    "azureWebPubSub.webPubSub.create": "Create Service",
    "azureWebPubSub.webPubSub.delete": "Delete Service",
    "azureWebPubSub.webPubSub.openLiveTraceTool": "Open Live Trace Tool",
    "azureWebPubSub.webPubSub.copyConnectionString": "Copy Service Connection String",
    "azureWebPubSub.webPubSub.copyEndpoint": "Copy Service Endpoint",
    "azureWebPubSub.hub.create": "Create Hub",
    "azureWebPubSub.hub.delete": "Delete Hub",
    "azureWebPubSub.webPubSub.createInPortal": "Create Web PubSub Service in Portal",
    "azureWebPubSub.webPubSub.create.info": "Create Web PubSub Service in Azure Portal.",
    "azureWebPubSub.webPubSub.openPublicEndpoint": "Access Public Endpoint",
    "azureWebPubSub.webPubSub.openTestEndpoint": "Access Test Endpoint",
    "azureWebPubSub.webPubSub.assignEndpoint": "Assign Public Endpoint",
    "azureWebPubSub.webPubSub.unassignEndpoint": "Unassign Public Endpoint",
    "azureWebPubSub.webPubSub.deploy": "Deploy",
    "azureWebPubSub.webPubSub.scale": "Scale",
    "azureWebPubSub.webPubSub.enableRemoteDebugging": "Enable Remote Debugging",
    "azureWebPubSub.webPubSub.disableRemoteDebugging": "Disable Remote Debugging",
    "azureWebPubSub.webPubSub.instance.startRemoteDebugging": "Attach Debugger",
    "azureWebPubSub.webPubSub.instance.startStreamingLog": "Start Streaming Logs",
    "azureWebPubSub.webPubSub.instance.stopStreamingLog": "Stop Streaming Logs",
    "azureWebPubSub.deleteConfirmation": "The behavior to use when confirming delete of a Azure Web PubSub.",
    "azureWebPubSub.deleteConfirmation.EnterName": "Prompts with an input box where you enter the Azure Web PubSub name to delete.",
    "azureWebPubSub.deleteConfirmation.ClickButton": "Prompts with a warning dialog where you click a button to delete.",
    "azureWebPubSub.webPubSub.helloWorld": "hello"
}
